zeropip/__init__.py
zeropip/installer.py
zeropip/saver.py
zeropip-2.0.0.dist-info/LICENSE
zeropip-2.0.0.dist-info/METADATA
zeropip-2.0.0.dist-info/WHEEL
zeropip-2.0.0.dist-info/top_level.txt
zeropip-2.0.0.dist-info/RECORD
