Metadata-Version: 2.2
Name: zeropip
Version: 2.0.0
Summary: zip 기반 AI 모델 복원 & 저장 도구
Home-page: https://github.com/blueradiance/zeropip
Author: blueradiance
Author-email: blueradiance@example.com
Classifier: Programming Language :: Python :: 3
Classifier: License :: OSI Approved :: MIT License
Classifier: Operating System :: OS Independent
Requires-Python: >=3.7
License-File: LICENSE
Dynamic: author
Dynamic: author-email
Dynamic: classifier
Dynamic: description
Dynamic: description-content-type
Dynamic: home-page
Dynamic: requires-python
Dynamic: summary
